README.rst
setup.py
bitpack/__init__.py
bitpack/field.py
bitpack/helpers.py
bitpack/stream.py
bitpack/utils.py
bitpack.egg-info/PKG-INFO
bitpack.egg-info/SOURCES.txt
bitpack.egg-info/dependency_links.txt
bitpack.egg-info/requires.txt
bitpack.egg-info/top_level.txt
tests/__init__.py
tests/test_field.py
tests/test_stream.py
tests/test_utils.py